pypqd/__init__.py
pypqd/auxiliary.py
pypqd/synthetic.py
pypqd-0.1.2.dist-info/LICENSE
pypqd-0.1.2.dist-info/METADATA
pypqd-0.1.2.dist-info/WHEEL
pypqd-0.1.2.dist-info/RECORD
